LICENSE
MANIFEST.in
README.rst
setup.py
doc/Makefile
doc/api.rst
doc/conf.py
doc/guide.rst
doc/index.rst
doc/tutorial.rst
doc/_build/html/_sources/api.rst.txt
doc/_build/html/_sources/guide.rst.txt
doc/_build/html/_sources/index.rst.txt
doc/_build/html/_sources/tutorial.rst.txt
moiety_modeling/__init__.py
moiety_modeling/__main__.py
moiety_modeling/analysis.py
moiety_modeling/cli.py
moiety_modeling/model.py
moiety_modeling/modeling.py
moiety_modeling.egg-info/PKG-INFO
moiety_modeling.egg-info/SOURCES.txt
moiety_modeling.egg-info/dependency_links.txt
moiety_modeling.egg-info/requires.txt
moiety_modeling.egg-info/top_level.txt