Metadata-Version: 1.1
Name: moiety-modeling
Version: 1.0.2
Summary: Moiety Modeling Implementation
Home-page: https://github.com/MoseleyBioinformaticsLab/moiety_modeling.git
Author: Huan Jin
Author-email: hji236@g.uky.edu
License: The Clear BSD License
Keywords: moiety modeling model optimization model selection
Platform: any
Classifier: Development Status :: 4 - Beta
Classifier: Environment :: Console
Classifier: Intended Audience :: Developers
Classifier: Intended Audience :: Science/Research
Classifier: License :: OSI Approved :: BSD License
Classifier: Operating System :: OS Independent
Classifier: Programming Language :: Python :: 3.5
Classifier: Programming Language :: Python :: 3.6
Classifier: Programming Language :: Python :: 3.7
